{
  "sections": {
    "main": {
      "type": "main-product",
      "blocks": {
        "vendor": {
          "type": "text",
          "settings": {
            "text": "{{ product.vendor }}",
            "text_style": "uppercase"
          }
        },
        "title": {
          "type": "title",
          "settings": {
          }
        },
        "14c52b56-ef5e-4313-a6db-73378e1be16a": {
          "type": "text",
          "settings": {
            "text": "{{ product.metafields.product.subtitle.value }}",
            "text_style": "subtitle"
          }
        },
        "292c51bc-2551-4e25-8482-a0428dac4648": {
          "type": "custom_liquid",
          "settings": {
            "custom_liquid": ""
          }
        },
        "20232a5b-fb1d-47df-bf99-6a3cc787a0da": {
          "type": "shopify:\/\/apps\/product-reviews\/blocks\/star_rating\/bae150af-8da8-48b2-9867-398188115e5f",
          "settings": {
            "stars_fill_color": "#121212",
            "star_size": 15,
            "text_align": "flex-start",
            "product": "{{product}}",
            "stars_text_empty": "Escribe una opinión"
          }
        },
        "subtitle": {
          "type": "text",
          "settings": {
            "text": "{{ product.metafields.descriptors.subtitle.value }}",
            "text_style": "subtitle"
          }
        },
        "price": {
          "type": "price",
          "settings": {
          }
        },
        "variant_picker": {
          "type": "variant_picker",
          "settings": {
            "picker_type": "button"
          }
        },
        "quantity_selector": {
          "type": "quantity_selector",
          "settings": {
          }
        },
        "buy_buttons": {
          "type": "buy_buttons",
          "settings": {
            "show_dynamic_checkout": true
          }
        },
        "description": {
          "type": "description",
          "settings": {
          }
        },
        "share": {
          "type": "share",
          "settings": {
            "share_label": "Compartir"
          }
        }
      },
      "block_order": [
        "vendor",
        "title",
        "14c52b56-ef5e-4313-a6db-73378e1be16a",
        "292c51bc-2551-4e25-8482-a0428dac4648",
        "20232a5b-fb1d-47df-bf99-6a3cc787a0da",
        "subtitle",
        "price",
        "variant_picker",
        "quantity_selector",
        "buy_buttons",
        "description",
        "share"
      ],
      "settings": {
        "enable_sticky_info": true,
        "hide_variants": true,
        "enable_video_looping": false
      }
    },
    "product-recommendations": {
      "type": "product-recommendations",
      "settings": {
        "heading": "También te puede interesar ❤️",
        "image_ratio": "adapt",
        "show_secondary_image": false,
        "add_image_padding": true,
        "show_image_outline": false,
        "show_vendor": false,
        "show_rating": false
      }
    },
    "1634748305156a652a": {
      "type": "apps",
      "blocks": {
        "190f81b4-d0b0-445a-a24d-7c8132c55b22": {
          "type": "shopify:\/\/apps\/product-reviews\/blocks\/reviews\/bae150af-8da8-48b2-9867-398188115e5f",
          "settings": {
          }
        }
      },
      "block_order": [
        "190f81b4-d0b0-445a-a24d-7c8132c55b22"
      ],
      "settings": {
        "include_margins": true
      }
    }
  },
  "order": [
    "main",
    "product-recommendations",
    "1634748305156a652a"
  ]
}
